{"v":"4.5.9","fr":30,"ip":0,"op":34,"w":140,"h":100,"ddd":0,"assets":[],"layers":[{"ddd":0,"ind":0,"ty":4,"nm":"Sign in completed Outlines","ks":{"o":{"a":1,"k":[{"i":{"x":[0.833],"y":[0.833]},"o":{"x":[0.167],"y":[0.167]},"n":["0p833_0p833_0p167_0p167"],"t":0,"s":[0],"e":[0]},{"i":{"x":[0.833],"y":[0.833]},"o":{"x":[0.167],"y":[0.167]},"n":["0p833_0p833_0p167_0p167"],"t":13,"s":[0],"e":[100]},{"t":18}]},"r":{"a":0,"k":0},"p":{"a":1,"k":[{"i":{"x":0.833,"y":0.833},"o":{"x":0.167,"y":0.167},"n":"0p833_0p833_0p167_0p167","t":13,"s":[66.875,76.75,0],"e":[64.875,19.75,0],"to":[-0.33333334326744,-9.5,0],"ti":[-0.83333331346512,8.83333301544189,0]},{"i":{"x":0.833,"y":0.833},"o":{"x":0.167,"y":0.167},"n":"0p833_0p833_0p167_0p167","t":18,"s":[64.875,19.75,0],"e":[71.875,23.75,0],"to":[0.83333331346512,-8.83333301544189,0],"ti":[-1.16666662693024,-0.66666668653488,0]},{"t":20}]},"a":{"a":0,"k":[44,-2,0]},"s":{"a":1,"k":[{"i":{"x":[0.833,0.833,0.833],"y":[0.833,0.833,0.833]},"o":{"x":[0.167,0.167,0.167],"y":[0.167,0.167,0.167]},"n":["0p833_0p833_0p167_0p167","0p833_0p833_0p167_0p167","0p833_0p833_0p167_0p167"],"t":13,"s":[0,100,100],"e":[100,100,100]},{"t":19}]}},"ao":0,"shapes":[{"ty":"gr","it":[{"ind":0,"ty":"sh","ks":{"a":0,"k":{"i":[[0,0],[-0.542,-0.498],[-0.957,0],[-0.62,0.376],[0,0.874],[0.486,0.369],[0.517,0.122],[0,0],[0.205,0.115],[0,0.387],[-0.264,0.265],[-0.604,0],[-0.312,-0.412],[-0.052,-0.422],[0,0],[0.563,0.399],[0.805,0],[0.477,-0.455],[0,-0.709],[-0.486,-0.329],[-0.676,-0.158],[0,0],[-0.264,-0.179],[0,-0.43],[0.614,-0.222],[0.386,0],[0.341,0.523],[0.024,0.448]],"o":[[-0.011,0.852],[0.541,0.501],[0.821,0],[0.62,-0.376],[0,-0.702],[-0.281,-0.211],[0,0],[-0.722,-0.172],[-0.312,-0.179],[0,-0.351],[0.264,-0.265],[0.748,0],[0.168,0.226],[0,0],[0,-0.877],[-0.563,-0.399],[-0.875,0],[-0.477,0.455],[0,0.655],[0.281,0.19],[0,0],[0.562,0.133],[0.26,0.183],[0,0.573],[-0.317,0.115],[-0.862,0],[-0.179,-0.279],[0,0]],"v":[[0.532,-2.546],[1.328,-0.521],[3.575,0.231],[5.736,-0.333],[6.666,-2.208],[5.937,-3.813],[4.74,-4.313],[3.668,-4.565],[2.278,-4.995],[1.81,-5.844],[2.207,-6.768],[3.509,-7.165],[5.101,-6.547],[5.43,-5.575],[6.435,-5.575],[5.59,-7.49],[3.539,-8.089],[1.511,-7.407],[0.795,-5.661],[1.523,-4.184],[2.959,-3.663],[3.995,-3.421],[5.233,-2.954],[5.624,-2.036],[4.703,-0.843],[3.647,-0.671],[1.841,-1.456],[1.536,-2.546]],"c":true}},"nm":"S","mn":"ADBE Vector Shape - Group"},{"ty":"fl","c":{"a":0,"k":[0.068,0.068,0.068,1]},"o":{"a":0,"k":100},"r":1,"nm":"Fill 1","mn":"ADBE Vector Graphic - Fill"},{"ty":"tr","p":{"a":0,"k":[0,0],"ix":2},"a":{"a":0,"k":[0,0],"ix":1},"s":{"a":0,"k":[100,100],"ix":3},"r":{"a":0,"k":0,"ix":6},"o":{"a":0,"k":100,"ix":7},"sk":{"a":0,"k":0,"ix":4},"sa":{"a":0,"k":0,"ix":5},"nm":"Transform"}],"nm":"S","np":3,"mn":"ADBE Vector Group"},{"ty":"gr","it":[{"ind":0,"ty":"sh","ks":{"a":0,"k":{"i":[[0,0],[0,0],[0,0],[0,0]],"o":[[0,0],[0,0],[0,0],[0,0]],"v":[[8.046,0],[9.029,0],[9.029,-5.726],[8.046,-5.726]],"c":true}},"nm":"i","mn":"ADBE Vector Shape - Group"},{"ind":1,"ty":"sh","ks":{"a":0,"k":{"i":[[0,0],[0,0],[0,0],[0,0]],"o":[[0,0],[0,0],[0,0],[0,0]],"v":[[8.046,-6.794],[9.029,-6.794],[9.029,-7.89],[8.046,-7.89]],"c":true}},"nm":"i","mn":"ADBE Vector Shape - Group"},{"ty":"mm","mm":1,"nm":"Merge Paths 1","mn":"ADBE Vector Filter - Merge"},{"ty":"fl","c":{"a":0,"k":[0.068,0.068,0.068,1]},"o":{"a":0,"k":100},"r":1,"nm":"Fill 1","mn":"ADBE Vector Graphic - Fill"},{"ty":"tr","p":{"a":0,"k":[0,0],"ix":2},"a":{"a":0,"k":[0,0],"ix":1},"s":{"a":0,"k":[100,100],"ix":3},"r":{"a":0,"k":0,"ix":6},"o":{"a":0,"k":100,"ix":7},"sk":{"a":0,"k":0,"ix":4},"sa":{"a":0,"k":0,"ix":5},"nm":"Transform"}],"nm":"i","np":5,"mn":"ADBE Vector Group"},{"ty":"gr","it":[{"ind":0,"ty":"sh","ks":{"a":0,"k":{"i":[[0.449,0],[0.469,-0.541],[0,-0.963],[-0.465,-0.442],[-0.621,0],[-0.271,0.143],[-0.193,0.294],[0.135,-0.308],[0.737,0],[0.217,0.215],[0.046,0.258],[0,0],[-0.421,-0.278],[-0.617,0],[-0.4,0.781],[0,0.73],[0,0],[0,0],[0,0],[0.182,0.125]],"o":[[-0.663,0],[-0.469,0.541],[0,1.021],[0.465,0.442],[0.446,0],[0.271,-0.143],[0.011,0.791],[-0.228,0.523],[-0.467,0],[-0.139,-0.14],[0,0],[0.05,0.591],[0.421,0.277],[1.11,0],[0.214,-0.423],[0,0],[0,0],[0,0],[-0.189,-0.24],[-0.335,-0.222]],"v":[[12.511,-5.854],[10.812,-5.043],[10.108,-2.788],[10.807,-0.594],[12.436,0.07],[13.511,-0.145],[14.207,-0.8],[14.02,0.849],[12.572,1.633],[11.546,1.311],[11.269,0.714],[10.286,0.714],[10.992,2.017],[12.55,2.433],[14.815,1.262],[15.136,-0.467],[15.136,-5.699],[14.244,-5.699],[14.244,-4.974],[13.688,-5.521]],"c":true}},"nm":"g","mn":"ADBE Vector Shape - Group"},{"ind":1,"ty":"sh","ks":{"a":0,"k":{"i":[[0,-0.713],[0.157,-0.354],[0.691,0],[0.262,0.338],[0,0.648],[-0.132,0.34],[-0.677,0],[-0.292,-0.344]],"o":[[0,0.473],[-0.281,0.627],[-0.442,0],[-0.262,-0.338],[0,-0.551],[0.249,-0.637],[0.452,0],[0.292,0.344]],"v":[[14.244,-2.9],[14.009,-1.66],[12.55,-0.72],[11.495,-1.227],[11.102,-2.707],[11.3,-4.044],[12.689,-5],[13.806,-4.485]],"c":true}},"nm":"g","mn":"ADBE Vector Shape - Group"},{"ty":"mm","mm":1,"nm":"Merge Paths 1","mn":"ADBE Vector Filter - Merge"},{"ty":"fl","c":{"a":0,"k":[0.068,0.068,0.068,1]},"o":{"a":0,"k":100},"r":1,"nm":"Fill 1","mn":"ADBE Vector Graphic - Fill"},{"ty":"tr","p":{"a":0,"k":[0,0],"ix":2},"a":{"a":0,"k":[0,0],"ix":1},"s":{"a":0,"k":[100,100],"ix":3},"r":{"a":0,"k":0,"ix":6},"o":{"a":0,"k":100,"ix":7},"sk":{"a":0,"k":0,"ix":4},"sa":{"a":0,"k":0,"ix":5},"nm":"Transform"}],"nm":"g","np":5,"mn":"ADBE Vector Group"},{"ty":"gr","it":[{"ind":0,"ty":"sh","ks":{"a":0,"k":{"i":[[0,0],[0,0],[0,0],[-0.048,0.202],[-0.161,0.19],[-0.265,0.079],[-0.229,0],[-0.172,-0.358],[0,-0.351],[0,0],[0,0],[0,0],[0.158,0.312],[0.816,0],[0.304,-0.147],[0.272,-0.337],[0,0],[0,0]],"o":[[0,0],[0,0],[0,-0.376],[0.048,-0.202],[0.201,-0.236],[0.147,-0.046],[0.451,0],[0.104,0.215],[0,0],[0,0],[0,0],[0,-0.58],[-0.287,-0.569],[-0.372,0],[-0.304,0.147],[0,0],[0,0],[0,0]],"v":[[16.607,0],[17.574,0],[17.574,-3.013],[17.647,-3.881],[17.961,-4.469],[18.659,-4.941],[19.223,-5.011],[20.158,-4.474],[20.313,-3.625],[20.313,0],[21.296,0],[21.296,-3.69],[21.06,-5.027],[19.406,-5.881],[18.391,-5.661],[17.526,-4.936],[17.526,-5.752],[16.607,-5.752]],"c":true}},"nm":"n","mn":"ADBE Vector Shape - Group"},{"ty":"fl","c":{"a":0,"k":[0.068,0.068,0.068,1]},"o":{"a":0,"k":100},"r":1,"nm":"Fill 1","mn":"ADBE Vector Graphic - Fill"},{"ty":"tr","p":{"a":0,"k":[0,0],"ix":2},"a":{"a":0,"k":[0,0],"ix":1},"s":{"a":0,"k":[100,100],"ix":3},"r":{"a":0,"k":0,"ix":6},"o":{"a":0,"k":100,"ix":7},"sk":{"a":0,"k":0,"ix":4},"sa":{"a":0,"k":0,"ix":5},"nm":"Transform"}],"nm":"n","np":3,"mn":"ADBE Vector Group"},{"ty":"gr","it":[{"ind":0,"ty":"sh","ks":{"a":0,"k":{"i":[[0,0],[0,0],[0,0],[0,0]],"o":[[0,0],[0,0],[0,0],[0,0]],"v":[[25.781,0],[26.764,0],[26.764,-5.726],[25.781,-5.726]],"c":true}},"nm":"i","mn":"ADBE Vector Shape - Group"},{"ind":1,"ty":"sh","ks":{"a":0,"k":{"i":[[0,0],[0,0],[0,0],[0,0]],"o":[[0,0],[0,0],[0,0],[0,0]],"v":[[25.781,-6.794],[26.764,-6.794],[26.764,-7.89],[25.781,-7.89]],"c":true}},"nm":"i","mn":"ADBE Vector Shape - Group"},{"ty":"mm","mm":1,"nm":"Merge Paths 1","mn":"ADBE Vector Filter - Merge"},{"ty":"fl","c":{"a":0,"k":[0.068,0.068,0.068,1]},"o":{"a":0,"k":100},"r":1,"nm":"Fill 1","mn":"ADBE Vector Graphic - Fill"},{"ty":"tr","p":{"a":0,"k":[0,0],"ix":2},"a":{"a":0,"k":[0,0],"ix":1},"s":{"a":0,"k":[100,100],"ix":3},"r":{"a":0,"k":0,"ix":6},"o":{"a":0,"k":100,"ix":7},"sk":{"a":0,"k":0,"ix":4},"sa":{"a":0,"k":0,"ix":5},"nm":"Transform"}],"nm":"i","np":5,"mn":"ADBE Vector Group"},{"ty":"gr","it":[{"ind":0,"ty":"sh","ks":{"a":0,"k":{"i":[[0,0],[0,0],[0,0],[-0.048,0.202],[-0.161,0.19],[-0.265,0.079],[-0.229,0],[-0.172,-0.358],[0,-0.351],[0,0],[0,0],[0,0],[0.158,0.312],[0.816,0],[0.304,-0.147],[0.272,-0.337],[0,0],[0,0]],"o":[[0,0],[0,0],[0,-0.376],[0.048,-0.202],[0.201,-0.236],[0.147,-0.046],[0.451,0],[0.104,0.215],[0,0],[0,0],[0,0],[0,-0.58],[-0.287,-0.569],[-0.372,0],[-0.304,0.147],[0,0],[0,0],[0,0]],"v":[[28.225,0],[29.192,0],[29.192,-3.013],[29.264,-3.881],[29.579,-4.469],[30.277,-4.941],[30.841,-5.011],[31.775,-4.474],[31.931,-3.625],[31.931,0],[32.914,0],[32.914,-3.69],[32.678,-5.027],[31.023,-5.881],[30.008,-5.661],[29.144,-4.936],[29.144,-5.752],[28.225,-5.752]],"c":true}},"nm":"n","mn":"ADBE Vector Shape - Group"},{"ty":"fl","c":{"a":0,"k":[0.068,0.068,0.068,1]},"o":{"a":0,"k":100},"r":1,"nm":"Fill 1","mn":"ADBE Vector Graphic - Fill"},{"ty":"tr","p":{"a":0,"k":[0,0],"ix":2},"a":{"a":0,"k":[0,0],"ix":1},"s":{"a":0,"k":[100,100],"ix":3},"r":{"a":0,"k":0,"ix":6},"o":{"a":0,"k":100,"ix":7},"sk":{"a":0,"k":0,"ix":4},"sa":{"a":0,"k":0,"ix":5},"nm":"Transform"}],"nm":"n","np":3,"mn":"ADBE Vector Group"},{"ty":"gr","it":[{"ind":0,"ty":"sh","ks":{"a":0,"k":{"i":[[0.648,0],[0.491,-0.562],[0,-1.01],[-0.448,-0.55],[-0.752,0],[-0.43,0.353],[-0.107,0.763],[0,0],[0.234,-0.244],[0.401,0],[0.243,0.393],[0,0.576],[-0.172,0.39],[-0.616,0],[-0.204,-0.234],[-0.057,-0.354],[0,0],[0.406,0.315]],"o":[[-0.759,0],[-0.491,0.562],[0,0.824],[0.448,0.55],[0.67,0],[0.43,-0.353],[0,0],[-0.09,0.424],[-0.235,0.244],[-0.523,0],[-0.244,-0.393],[0,-0.572],[0.265,-0.601],[0.451,0],[0.204,0.235],[0,0],[-0.082,-0.77],[-0.406,-0.315]],"v":[[39.617,-5.919],[37.743,-5.076],[37.007,-2.718],[37.678,-0.658],[39.478,0.167],[41.126,-0.363],[41.932,-2.036],[40.992,-2.036],[40.506,-1.033],[39.553,-0.666],[38.403,-1.256],[38.038,-2.71],[38.296,-4.153],[39.617,-5.054],[40.6,-4.702],[40.992,-3.819],[41.932,-3.819],[41.199,-5.446]],"c":true}},"nm":"c","mn":"ADBE Vector Shape - Group"},{"ty":"fl","c":{"a":0,"k":[0.068,0.068,0.068,1]},"o":{"a":0,"k":100},"r":1,"nm":"Fill 1","mn":"ADBE Vector Graphic - Fill"},{"ty":"tr","p":{"a":0,"k":[0,0],"ix":2},"a":{"a":0,"k":[0,0],"ix":1},"s":{"a":0,"k":[100,100],"ix":3},"r":{"a":0,"k":0,"ix":6},"o":{"a":0,"k":100,"ix":7},"sk":{"a":0,"k":0,"ix":4},"sa":{"a":0,"k":0,"ix":5},"nm":"Transform"}],"nm":"c","np":3,"mn":"ADBE Vector Group"},{"ty":"gr","it":[{"ind":0,"ty":"sh","ks":{"a":0,"k":{"i":[[0.634,0],[0.266,0.408],[0,0.612],[-0.266,0.451],[-0.584,0],[-0.269,-0.529],[0,-0.536],[0.235,-0.485]],"o":[[-0.577,0],[-0.266,-0.408],[0,-0.637],[0.266,-0.451],[0.659,0],[0.17,0.336],[0,0.594],[-0.235,0.485]],"v":[[45.163,-0.628],[43.899,-1.24],[43.5,-2.769],[43.899,-4.4],[45.173,-5.076],[46.565,-4.282],[46.82,-2.973],[46.467,-1.355]],"c":true}},"nm":"o","mn":"ADBE Vector Shape - Group"},{"ind":1,"ty":"sh","ks":{"a":0,"k":{"i":[[0.736,0],[0.487,-0.572],[0,-0.966],[-0.462,-0.535],[-0.786,0],[-0.448,0.605],[0,0.927],[0.508,0.494]],"o":[[-0.821,0],[-0.487,0.572],[0,0.902],[0.462,0.535],[0.942,0],[0.448,-0.605],[0,-0.959],[-0.508,-0.494]],"v":[[45.2,-5.919],[43.237,-5.06],[42.507,-2.753],[43.2,-0.598],[45.072,0.204],[47.158,-0.703],[47.83,-3],[47.067,-5.178]],"c":true}},"nm":"o","mn":"ADBE Vector Shape - Group"},{"ty":"mm","mm":1,"nm":"Merge Paths 1","mn":"ADBE Vector Filter - Merge"},{"ty":"fl","c":{"a":0,"k":[0.068,0.068,0.068,1]},"o":{"a":0,"k":100},"r":1,"nm":"Fill 1","mn":"ADBE Vector Graphic - Fill"},{"ty":"tr","p":{"a":0,"k":[0,0],"ix":2},"a":{"a":0,"k":[0,0],"ix":1},"s":{"a":0,"k":[100,100],"ix":3},"r":{"a":0,"k":0,"ix":6},"o":{"a":0,"k":100,"ix":7},"sk":{"a":0,"k":0,"ix":4},"sa":{"a":0,"k":0,"ix":5},"nm":"Transform"}],"nm":"o","np":5,"mn":"ADBE Vector Group"},{"ty":"gr","it":[{"ind":0,"ty":"sh","ks":{"a":0,"k":{"i":[[0,0],[0,0],[0,0],[-0.299,0.283],[-0.365,0],[-0.147,-0.269],[0,-0.39],[0,0],[0,0],[0,0],[-0.274,0.254],[-0.38,0],[-0.192,-0.143],[0,-0.383],[0,0],[0,0],[0,0],[0.15,0.301],[0.773,0],[0.29,-0.149],[0.215,-0.308],[0.158,0.129],[0.458,0],[0.319,-0.218],[0.229,-0.283],[0,0],[0,0]],"o":[[0,0],[0,0],[0,-0.741],[0.299,-0.283],[0.401,0],[0.093,0.179],[0,0],[0,0],[0,0],[0,-0.594],[0.274,-0.254],[0.276,0],[0.192,0.143],[0,0],[0,0],[0,0],[0,-0.508],[-0.279,-0.559],[-0.362,0],[-0.29,0.149],[-0.129,-0.251],[-0.279,-0.226],[-0.405,0],[-0.186,0.129],[0,0],[0,0],[0,0]],"v":[[49.017,0],[49.983,0],[49.983,-3.051],[50.432,-4.587],[51.428,-5.011],[52.25,-4.608],[52.39,-3.754],[52.39,0],[53.373,0],[53.373,-3.346],[53.783,-4.619],[54.764,-5],[55.465,-4.786],[55.752,-3.996],[55.752,0],[56.756,0],[56.756,-3.83],[56.531,-5.043],[54.952,-5.881],[53.974,-5.658],[53.217,-4.974],[52.787,-5.543],[51.681,-5.881],[50.596,-5.554],[49.973,-4.936],[49.973,-5.752],[49.017,-5.752]],"c":true}},"nm":"m","mn":"ADBE Vector Shape - Group"},{"ty":"fl","c":{"a":0,"k":[0.068,0.068,0.068,1]},"o":{"a":0,"k":100},"r":1,"nm":"Fill 1","mn":"ADBE Vector Graphic - Fill"},{"ty":"tr","p":{"a":0,"k":[0,0],"ix":2},"a":{"a":0,"k":[0,0],"ix":1},"s":{"a":0,"k":[100,100],"ix":3},"r":{"a":0,"k":0,"ix":6},"o":{"a":0,"k":100,"ix":7},"sk":{"a":0,"k":0,"ix":4},"sa":{"a":0,"k":0,"ix":5},"nm":"Transform"}],"nm":"m","np":3,"mn":"ADBE Vector Group"},{"ty":"gr","it":[{"ind":0,"ty":"sh","ks":{"a":0,"k":{"i":[[0.453,0],[0.251,0.594],[0,0.444],[-0.133,0.358],[-0.672,0],[-0.252,-0.634],[0,-0.458],[0.3,-0.378]],"o":[[-0.668,0],[-0.133,-0.312],[0,-0.551],[0.248,-0.67],[0.668,0],[0.133,0.329],[0,0.752],[-0.3,0.378]],"v":[[60.607,-0.65],[59.228,-1.542],[59.028,-2.675],[59.228,-4.039],[60.607,-5.043],[61.987,-4.093],[62.187,-2.911],[61.737,-1.217]],"c":true}},"nm":"p","mn":"ADBE Vector Shape - Group"},{"ind":1,"ty":"sh","ks":{"a":0,"k":{"i":[[0,0],[0,0],[0,0],[-0.173,-0.107],[-0.435,0],[-0.417,0.34],[0,1.253],[0.456,0.5],[0.653,0],[0.327,-0.215],[0.194,-0.261],[0,0],[0,0]],"o":[[0,0],[0,0],[0.212,0.261],[0.295,0.19],[0.554,0],[0.658,-0.537],[0,-0.927],[-0.456,-0.5],[-0.442,0],[-0.23,0.143],[0,0],[0,0],[0,0]],"v":[[58.099,2.293],[59.066,2.293],[59.066,-0.645],[59.643,-0.091],[60.738,0.193],[62.193,-0.317],[63.18,-3.002],[62.496,-5.143],[60.832,-5.892],[59.68,-5.57],[59.044,-4.963],[59.044,-5.726],[58.099,-5.726]],"c":true}},"nm":"p","mn":"ADBE Vector Shape - Group"},{"ty":"mm","mm":1,"nm":"Merge Paths 1","mn":"ADBE Vector Filter - Merge"},{"ty":"fl","c":{"a":0,"k":[0.068,0.068,0.068,1]},"o":{"a":0,"k":100},"r":1,"nm":"Fill 1","mn":"ADBE Vector Graphic - Fill"},{"ty":"tr","p":{"a":0,"k":[0,0],"ix":2},"a":{"a":0,"k":[0,0],"ix":1},"s":{"a":0,"k":[100,100],"ix":3},"r":{"a":0,"k":0,"ix":6},"o":{"a":0,"k":100,"ix":7},"sk":{"a":0,"k":0,"ix":4},"sa":{"a":0,"k":0,"ix":5},"nm":"Transform"}],"nm":"p","np":5,"mn":"ADBE Vector Group"},{"ty":"gr","it":[{"ind":0,"ty":"sh","ks":{"a":0,"k":{"i":[[0,0],[0,0],[0,0],[0,0]],"o":[[0,0],[0,0],[0,0],[0,0]],"v":[[64.324,0],[65.291,0],[65.291,-7.89],[64.324,-7.89]],"c":true}},"nm":"l","mn":"ADBE Vector Shape - Group"},{"ty":"fl","c":{"a":0,"k":[0.068,0.068,0.068,1]},"o":{"a":0,"k":100},"r":1,"nm":"Fill 1","mn":"ADBE Vector Graphic - Fill"},{"ty":"tr","p":{"a":0,"k":[0,0],"ix":2},"a":{"a":0,"k":[0,0],"ix":1},"s":{"a":0,"k":[100,100],"ix":3},"r":{"a":0,"k":0,"ix":6},"o":{"a":0,"k":100,"ix":7},"sk":{"a":0,"k":0,"ix":4},"sa":{"a":0,"k":0,"ix":5},"nm":"Transform"}],"nm":"l","np":3,"mn":"ADBE Vector Group"},{"ty":"gr","it":[{"ind":0,"ty":"sh","ks":{"a":0,"k":{"i":[[0.406,0],[0.498,-0.576],[0,-0.924],[-0.495,-0.521],[-0.712,0],[-0.231,0.057],[-0.291,0.287],[-0.141,0.26],[-0.025,0.211],[0,0],[0.167,-0.194],[0.501,0],[0.256,0.354],[0.018,0.585],[0,0],[0.057,0.265],[0.192,0.29],[0.381,0.192]],"o":[[-0.804,0],[-0.498,0.577],[0,0.938],[0.495,0.521],[0.291,0],[0.43,-0.1],[0.174,-0.165],[0.141,-0.26],[0,0],[-0.07,0.255],[-0.298,0.335],[-0.536,0],[-0.256,-0.354],[0,0],[0,-0.58],[-0.064,-0.387],[-0.199,-0.304],[-0.381,-0.192]],"v":[[69.115,-5.881],[67.161,-5.017],[66.414,-2.766],[67.155,-0.577],[68.965,0.204],[69.749,0.118],[70.831,-0.462],[71.304,-1.098],[71.554,-1.805],[70.603,-1.805],[70.248,-1.13],[69.049,-0.628],[67.861,-1.159],[67.45,-2.567],[71.634,-2.567],[71.549,-3.835],[71.164,-4.85],[70.294,-5.594]],"c":true}},"nm":"e","mn":"ADBE Vector Shape - Group"},{"ind":1,"ty":"sh","ks":{"a":0,"k":{"i":[[0,0],[-0.298,0.32],[-0.44,0],[-0.263,-0.465],[-0.039,-0.419]],"o":[[0.018,-0.494],[0.298,-0.32],[0.614,0],[0.142,0.251],[0,0]],"v":[[67.472,-3.335],[67.946,-4.557],[69.053,-5.038],[70.369,-4.34],[70.641,-3.335]],"c":true}},"nm":"e","mn":"ADBE Vector Shape - Group"},{"ty":"mm","mm":1,"nm":"Merge Paths 1","mn":"ADBE Vector Filter - Merge"},{"ty":"fl","c":{"a":0,"k":[0.068,0.068,0.068,1]},"o":{"a":0,"k":100},"r":1,"nm":"Fill 1","mn":"ADBE Vector Graphic - Fill"},{"ty":"tr","p":{"a":0,"k":[0,0],"ix":2},"a":{"a":0,"k":[0,0],"ix":1},"s":{"a":0,"k":[100,100],"ix":3},"r":{"a":0,"k":0,"ix":6},"o":{"a":0,"k":100,"ix":7},"sk":{"a":0,"k":0,"ix":4},"sa":{"a":0,"k":0,"ix":5},"nm":"Transform"}],"nm":"e","np":5,"mn":"ADBE Vector Group"},{"ty":"gr","it":[{"ind":0,"ty":"sh","ks":{"a":0,"k":{"i":[[0,0],[0,0],[0,0],[0,0],[0,0],[-0.161,-0.231],[-0.451,0],[-0.12,0.014],[-0.111,0.032],[0,0],[0.054,-0.002],[0.046,0],[0.075,0.039],[0,0.201],[0,0],[0,0],[0,0],[0,0],[0,0],[0,0]],"o":[[0,0],[0,0],[0,0],[0,0],[0,0.369],[0.161,0.231],[0.14,0],[0.12,-0.014],[0,0],[-0.072,0.01],[-0.054,0.002],[-0.175,0],[-0.136,-0.068],[0,0],[0,0],[0,0],[0,0],[0,0],[0,0],[0,0]],"v":[[73.052,-5.752],[72.273,-5.752],[72.273,-4.963],[73.052,-4.963],[73.052,-1.155],[73.294,-0.255],[74.212,0.091],[74.602,0.07],[74.948,0],[74.948,-0.768],[74.76,-0.75],[74.61,-0.747],[74.234,-0.806],[74.03,-1.208],[74.03,-4.963],[74.948,-4.963],[74.948,-5.752],[74.03,-5.752],[74.03,-7.358],[73.052,-7.358]],"c":true}},"nm":"t","mn":"ADBE Vector Shape - Group"},{"ty":"fl","c":{"a":0,"k":[0.068,0.068,0.068,1]},"o":{"a":0,"k":100},"r":1,"nm":"Fill 1","mn":"ADBE Vector Graphic - Fill"},{"ty":"tr","p":{"a":0,"k":[0,0],"ix":2},"a":{"a":0,"k":[0,0],"ix":1},"s":{"a":0,"k":[100,100],"ix":3},"r":{"a":0,"k":0,"ix":6},"o":{"a":0,"k":100,"ix":7},"sk":{"a":0,"k":0,"ix":4},"sa":{"a":0,"k":0,"ix":5},"nm":"Transform"}],"nm":"t","np":3,"mn":"ADBE Vector Group"},{"ty":"gr","it":[{"ind":0,"ty":"sh","ks":{"a":0,"k":{"i":[[0.406,0],[0.498,-0.576],[0,-0.924],[-0.495,-0.521],[-0.712,0],[-0.231,0.057],[-0.291,0.287],[-0.141,0.26],[-0.025,0.211],[0,0],[0.167,-0.194],[0.501,0],[0.256,0.354],[0.018,0.585],[0,0],[0.057,0.265],[0.192,0.29],[0.381,0.192]],"o":[[-0.804,0],[-0.498,0.577],[0,0.938],[0.495,0.521],[0.291,0],[0.43,-0.1],[0.174,-0.165],[0.141,-0.26],[0,0],[-0.07,0.255],[-0.298,0.335],[-0.536,0],[-0.256,-0.354],[0,0],[0,-0.58],[-0.064,-0.387],[-0.199,-0.304],[-0.381,-0.192]],"v":[[78.288,-5.881],[76.335,-5.017],[75.587,-2.766],[76.329,-0.577],[78.139,0.204],[78.922,0.118],[80.004,-0.462],[80.478,-1.098],[80.728,-1.805],[79.777,-1.805],[79.422,-1.13],[78.223,-0.628],[77.034,-1.159],[76.624,-2.567],[80.808,-2.567],[80.723,-3.835],[80.338,-4.85],[79.468,-5.594]],"c":true}},"nm":"e","mn":"ADBE Vector Shape - Group"},{"ind":1,"ty":"sh","ks":{"a":0,"k":{"i":[[0,0],[-0.298,0.32],[-0.44,0],[-0.263,-0.465],[-0.039,-0.419]],"o":[[0.018,-0.494],[0.298,-0.32],[0.614,0],[0.142,0.251],[0,0]],"v":[[76.646,-3.335],[77.12,-4.557],[78.227,-5.038],[79.543,-4.34],[79.814,-3.335]],"c":true}},"nm":"e","mn":"ADBE Vector Shape - Group"},{"ty":"mm","mm":1,"nm":"Merge Paths 1","mn":"ADBE Vector Filter - Merge"},{"ty":"fl","c":{"a":0,"k":[0.068,0.068,0.068,1]},"o":{"a":0,"k":100},"r":1,"nm":"Fill 1","mn":"ADBE Vector Graphic - Fill"},{"ty":"tr","p":{"a":0,"k":[0,0],"ix":2},"a":{"a":0,"k":[0,0],"ix":1},"s":{"a":0,"k":[100,100],"ix":3},"r":{"a":0,"k":0,"ix":6},"o":{"a":0,"k":100,"ix":7},"sk":{"a":0,"k":0,"ix":4},"sa":{"a":0,"k":0,"ix":5},"nm":"Transform"}],"nm":"e","np":5,"mn":"ADBE Vector Group"},{"ty":"gr","it":[{"ind":0,"ty":"sh","ks":{"a":0,"k":{"i":[[0,0.616],[-0.301,0.372],[-0.485,0],[-0.296,-0.349],[0,-0.727],[0.287,-0.385],[0.445,0],[0.26,0.415]],"o":[[0,-0.723],[0.301,-0.372],[0.435,0],[0.296,0.349],[0,0.72],[-0.287,0.385],[-0.574,0],[-0.26,-0.415]],"v":[[82.645,-2.809],[83.097,-4.453],[84.275,-5.011],[85.37,-4.488],[85.814,-2.874],[85.384,-1.217],[84.286,-0.639],[83.035,-1.262]],"c":true}},"nm":"d","mn":"ADBE Vector Shape - Group"},{"ind":1,"ty":"sh","ks":{"a":0,"k":{"i":[[0.439,0],[0.426,-0.614],[0,-0.838],[-0.467,-0.539],[-0.638,0],[-0.307,0.158],[-0.225,0.354],[0,0],[0,0],[0,0],[0,0],[0,0],[0.171,0.107]],"o":[[-0.792,0],[-0.426,0.614],[0,0.895],[0.467,0.539],[0.396,0],[0.307,-0.158],[0,0],[0,0],[0,0],[0,0],[0,0],[-0.218,-0.269],[-0.296,-0.186]],"v":[[84.091,-5.854],[82.264,-4.933],[81.625,-2.755],[82.325,-0.604],[83.984,0.204],[85.038,-0.032],[85.835,-0.8],[85.835,0],[86.706,0],[86.706,-7.917],[85.776,-7.917],[85.776,-5.011],[85.193,-5.575]],"c":true}},"nm":"d","mn":"ADBE Vector Shape - Group"},{"ty":"mm","mm":1,"nm":"Merge Paths 1","mn":"ADBE Vector Filter - Merge"},{"ty":"fl","c":{"a":0,"k":[0.068,0.068,0.068,1]},"o":{"a":0,"k":100},"r":1,"nm":"Fill 1","mn":"ADBE Vector Graphic - Fill"},{"ty":"tr","p":{"a":0,"k":[0,0],"ix":2},"a":{"a":0,"k":[0,0],"ix":1},"s":{"a":0,"k":[100,100],"ix":3},"r":{"a":0,"k":0,"ix":6},"o":{"a":0,"k":100,"ix":7},"sk":{"a":0,"k":0,"ix":4},"sa":{"a":0,"k":0,"ix":5},"nm":"Transform"}],"nm":"d","np":5,"mn":"ADBE Vector Group"}],"ip":0,"op":52,"st":0,"bm":0,"sr":1},{"ddd":0,"ind":1,"ty":4,"nm":"Sign in Outlines","ks":{"o":{"a":1,"k":[{"i":{"x":[0.833],"y":[0.833]},"o":{"x":[0.167],"y":[0.167]},"n":["0p833_0p833_0p167_0p167"],"t":2,"s":[100],"e":[0]},{"t":6}]},"r":{"a":0,"k":0},"p":{"a":0,"k":[54.625,76.375,0]},"a":{"a":0,"k":[0,0,0]},"s":{"a":1,"k":[{"i":{"x":[0.833,0.833,0.833],"y":[0.833,0.833,0.833]},"o":{"x":[0.167,0.167,0.167],"y":[0.167,0.167,0.167]},"n":["0p833_0p833_0p167_0p167","0p833_0p833_0p167_0p167","0p833_0p833_0p167_0p167"],"t":2,"s":[100,100,100],"e":[0,0,100]},{"t":4}]}},"ao":0,"shapes":[{"ty":"gr","it":[{"ind":0,"ty":"sh","ks":{"a":0,"k":{"i":[[0,0],[-0.542,-0.498],[-0.957,0],[-0.62,0.376],[0,0.874],[0.486,0.369],[0.517,0.122],[0,0],[0.205,0.115],[0,0.387],[-0.264,0.265],[-0.604,0],[-0.312,-0.412],[-0.052,-0.422],[0,0],[0.563,0.399],[0.805,0],[0.477,-0.455],[0,-0.709],[-0.486,-0.329],[-0.676,-0.158],[0,0],[-0.264,-0.179],[0,-0.43],[0.614,-0.222],[0.386,0],[0.341,0.523],[0.024,0.448]],"o":[[-0.011,0.852],[0.541,0.501],[0.821,0],[0.62,-0.376],[0,-0.702],[-0.281,-0.211],[0,0],[-0.722,-0.172],[-0.312,-0.179],[0,-0.351],[0.264,-0.265],[0.748,0],[0.168,0.226],[0,0],[0,-0.877],[-0.563,-0.399],[-0.875,0],[-0.477,0.455],[0,0.655],[0.281,0.19],[0,0],[0.562,0.133],[0.26,0.183],[0,0.573],[-0.317,0.115],[-0.862,0],[-0.179,-0.279],[0,0]],"v":[[0.532,-2.546],[1.328,-0.521],[3.575,0.231],[5.736,-0.333],[6.666,-2.208],[5.937,-3.813],[4.74,-4.313],[3.668,-4.565],[2.278,-4.995],[1.81,-5.844],[2.207,-6.768],[3.509,-7.165],[5.101,-6.547],[5.43,-5.575],[6.435,-5.575],[5.59,-7.49],[3.539,-8.089],[1.511,-7.407],[0.795,-5.661],[1.523,-4.184],[2.959,-3.663],[3.995,-3.421],[5.233,-2.954],[5.624,-2.036],[4.703,-0.843],[3.647,-0.671],[1.841,-1.456],[1.536,-2.546]],"c":true}},"nm":"S","mn":"ADBE Vector Shape - Group"},{"ty":"fl","c":{"a":0,"k":[0.068,0.068,0.068,1]},"o":{"a":0,"k":100},"r":1,"nm":"Fill 1","mn":"ADBE Vector Graphic - Fill"},{"ty":"tr","p":{"a":0,"k":[0,0],"ix":2},"a":{"a":0,"k":[0,0],"ix":1},"s":{"a":0,"k":[100,100],"ix":3},"r":{"a":0,"k":0,"ix":6},"o":{"a":0,"k":100,"ix":7},"sk":{"a":0,"k":0,"ix":4},"sa":{"a":0,"k":0,"ix":5},"nm":"Transform"}],"nm":"S","np":3,"mn":"ADBE Vector Group"},{"ty":"gr","it":[{"ind":0,"ty":"sh","ks":{"a":0,"k":{"i":[[0,0],[0,0],[0,0],[0,0]],"o":[[0,0],[0,0],[0,0],[0,0]],"v":[[8.046,0],[9.029,0],[9.029,-5.726],[8.046,-5.726]],"c":true}},"nm":"i","mn":"ADBE Vector Shape - Group"},{"ind":1,"ty":"sh","ks":{"a":0,"k":{"i":[[0,0],[0,0],[0,0],[0,0]],"o":[[0,0],[0,0],[0,0],[0,0]],"v":[[8.046,-6.794],[9.029,-6.794],[9.029,-7.89],[8.046,-7.89]],"c":true}},"nm":"i","mn":"ADBE Vector Shape - Group"},{"ty":"mm","mm":1,"nm":"Merge Paths 1","mn":"ADBE Vector Filter - Merge"},{"ty":"fl","c":{"a":0,"k":[0.068,0.068,0.068,1]},"o":{"a":0,"k":100},"r":1,"nm":"Fill 1","mn":"ADBE Vector Graphic - Fill"},{"ty":"tr","p":{"a":0,"k":[0,0],"ix":2},"a":{"a":0,"k":[0,0],"ix":1},"s":{"a":0,"k":[100,100],"ix":3},"r":{"a":0,"k":0,"ix":6},"o":{"a":0,"k":100,"ix":7},"sk":{"a":0,"k":0,"ix":4},"sa":{"a":0,"k":0,"ix":5},"nm":"Transform"}],"nm":"i","np":5,"mn":"ADBE Vector Group"},{"ty":"gr","it":[{"ind":0,"ty":"sh","ks":{"a":0,"k":{"i":[[0.449,0],[0.469,-0.541],[0,-0.963],[-0.465,-0.442],[-0.621,0],[-0.271,0.143],[-0.193,0.294],[0.135,-0.308],[0.737,0],[0.217,0.215],[0.046,0.258],[0,0],[-0.421,-0.278],[-0.617,0],[-0.4,0.781],[0,0.73],[0,0],[0,0],[0,0],[0.182,0.125]],"o":[[-0.663,0],[-0.469,0.541],[0,1.021],[0.465,0.442],[0.446,0],[0.271,-0.143],[0.011,0.791],[-0.228,0.523],[-0.467,0],[-0.139,-0.14],[0,0],[0.05,0.591],[0.421,0.277],[1.11,0],[0.214,-0.423],[0,0],[0,0],[0,0],[-0.189,-0.24],[-0.335,-0.222]],"v":[[12.511,-5.854],[10.812,-5.043],[10.108,-2.788],[10.807,-0.594],[12.436,0.07],[13.511,-0.145],[14.207,-0.8],[14.02,0.849],[12.572,1.633],[11.546,1.311],[11.269,0.714],[10.286,0.714],[10.992,2.017],[12.55,2.433],[14.815,1.262],[15.136,-0.467],[15.136,-5.699],[14.244,-5.699],[14.244,-4.974],[13.688,-5.521]],"c":true}},"nm":"g","mn":"ADBE Vector Shape - Group"},{"ind":1,"ty":"sh","ks":{"a":0,"k":{"i":[[0,-0.713],[0.157,-0.354],[0.691,0],[0.262,0.338],[0,0.648],[-0.132,0.34],[-0.677,0],[-0.292,-0.344]],"o":[[0,0.473],[-0.281,0.627],[-0.442,0],[-0.262,-0.338],[0,-0.551],[0.249,-0.637],[0.452,0],[0.292,0.344]],"v":[[14.244,-2.9],[14.009,-1.66],[12.55,-0.72],[11.495,-1.227],[11.102,-2.707],[11.3,-4.044],[12.689,-5],[13.806,-4.485]],"c":true}},"nm":"g","mn":"ADBE Vector Shape - Group"},{"ty":"mm","mm":1,"nm":"Merge Paths 1","mn":"ADBE Vector Filter - Merge"},{"ty":"fl","c":{"a":0,"k":[0.068,0.068,0.068,1]},"o":{"a":0,"k":100},"r":1,"nm":"Fill 1","mn":"ADBE Vector Graphic - Fill"},{"ty":"tr","p":{"a":0,"k":[0,0],"ix":2},"a":{"a":0,"k":[0,0],"ix":1},"s":{"a":0,"k":[100,100],"ix":3},"r":{"a":0,"k":0,"ix":6},"o":{"a":0,"k":100,"ix":7},"sk":{"a":0,"k":0,"ix":4},"sa":{"a":0,"k":0,"ix":5},"nm":"Transform"}],"nm":"g","np":5,"mn":"ADBE Vector Group"},{"ty":"gr","it":[{"ind":0,"ty":"sh","ks":{"a":0,"k":{"i":[[0,0],[0,0],[0,0],[-0.048,0.202],[-0.161,0.19],[-0.265,0.079],[-0.229,0],[-0.172,-0.358],[0,-0.351],[0,0],[0,0],[0,0],[0.158,0.312],[0.816,0],[0.304,-0.147],[0.272,-0.337],[0,0],[0,0]],"o":[[0,0],[0,0],[0,-0.376],[0.048,-0.202],[0.201,-0.236],[0.147,-0.046],[0.451,0],[0.104,0.215],[0,0],[0,0],[0,0],[0,-0.58],[-0.287,-0.569],[-0.372,0],[-0.304,0.147],[0,0],[0,0],[0,0]],"v":[[16.607,0],[17.574,0],[17.574,-3.013],[17.647,-3.881],[17.961,-4.469],[18.659,-4.941],[19.223,-5.011],[20.158,-4.474],[20.313,-3.625],[20.313,0],[21.296,0],[21.296,-3.69],[21.06,-5.027],[19.406,-5.881],[18.391,-5.661],[17.526,-4.936],[17.526,-5.752],[16.607,-5.752]],"c":true}},"nm":"n","mn":"ADBE Vector Shape - Group"},{"ty":"fl","c":{"a":0,"k":[0.068,0.068,0.068,1]},"o":{"a":0,"k":100},"r":1,"nm":"Fill 1","mn":"ADBE Vector Graphic - Fill"},{"ty":"tr","p":{"a":0,"k":[0,0],"ix":2},"a":{"a":0,"k":[0,0],"ix":1},"s":{"a":0,"k":[100,100],"ix":3},"r":{"a":0,"k":0,"ix":6},"o":{"a":0,"k":100,"ix":7},"sk":{"a":0,"k":0,"ix":4},"sa":{"a":0,"k":0,"ix":5},"nm":"Transform"}],"nm":"n","np":3,"mn":"ADBE Vector Group"},{"ty":"gr","it":[{"ind":0,"ty":"sh","ks":{"a":0,"k":{"i":[[0,0],[0,0],[0,0],[0,0]],"o":[[0,0],[0,0],[0,0],[0,0]],"v":[[25.781,0],[26.764,0],[26.764,-5.726],[25.781,-5.726]],"c":true}},"nm":"i","mn":"ADBE Vector Shape - Group"},{"ind":1,"ty":"sh","ks":{"a":0,"k":{"i":[[0,0],[0,0],[0,0],[0,0]],"o":[[0,0],[0,0],[0,0],[0,0]],"v":[[25.781,-6.794],[26.764,-6.794],[26.764,-7.89],[25.781,-7.89]],"c":true}},"nm":"i","mn":"ADBE Vector Shape - Group"},{"ty":"mm","mm":1,"nm":"Merge Paths 1","mn":"ADBE Vector Filter - Merge"},{"ty":"fl","c":{"a":0,"k":[0.068,0.068,0.068,1]},"o":{"a":0,"k":100},"r":1,"nm":"Fill 1","mn":"ADBE Vector Graphic - Fill"},{"ty":"tr","p":{"a":0,"k":[0,0],"ix":2},"a":{"a":0,"k":[0,0],"ix":1},"s":{"a":0,"k":[100,100],"ix":3},"r":{"a":0,"k":0,"ix":6},"o":{"a":0,"k":100,"ix":7},"sk":{"a":0,"k":0,"ix":4},"sa":{"a":0,"k":0,"ix":5},"nm":"Transform"}],"nm":"i","np":5,"mn":"ADBE Vector Group"},{"ty":"gr","it":[{"ind":0,"ty":"sh","ks":{"a":0,"k":{"i":[[0,0],[0,0],[0,0],[-0.048,0.202],[-0.161,0.19],[-0.265,0.079],[-0.229,0],[-0.172,-0.358],[0,-0.351],[0,0],[0,0],[0,0],[0.158,0.312],[0.816,0],[0.304,-0.147],[0.272,-0.337],[0,0],[0,0]],"o":[[0,0],[0,0],[0,-0.376],[0.048,-0.202],[0.201,-0.236],[0.147,-0.046],[0.451,0],[0.104,0.215],[0,0],[0,0],[0,0],[0,-0.58],[-0.287,-0.569],[-0.372,0],[-0.304,0.147],[0,0],[0,0],[0,0]],"v":[[28.225,0],[29.192,0],[29.192,-3.013],[29.264,-3.881],[29.579,-4.469],[30.277,-4.941],[30.841,-5.011],[31.775,-4.474],[31.931,-3.625],[31.931,0],[32.914,0],[32.914,-3.69],[32.678,-5.027],[31.023,-5.881],[30.008,-5.661],[29.144,-4.936],[29.144,-5.752],[28.225,-5.752]],"c":true}},"nm":"n","mn":"ADBE Vector Shape - Group"},{"ty":"fl","c":{"a":0,"k":[0.068,0.068,0.068,1]},"o":{"a":0,"k":100},"r":1,"nm":"Fill 1","mn":"ADBE Vector Graphic - Fill"},{"ty":"tr","p":{"a":0,"k":[0,0],"ix":2},"a":{"a":0,"k":[0,0],"ix":1},"s":{"a":0,"k":[100,100],"ix":3},"r":{"a":0,"k":0,"ix":6},"o":{"a":0,"k":100,"ix":7},"sk":{"a":0,"k":0,"ix":4},"sa":{"a":0,"k":0,"ix":5},"nm":"Transform"}],"nm":"n","np":3,"mn":"ADBE Vector Group"}],"ip":0,"op":52,"st":0,"bm":0,"sr":1},{"ddd":0,"ind":2,"ty":4,"nm":"Shape Layer 1","ks":{"o":{"a":0,"k":100},"r":{"a":0,"k":0},"p":{"a":0,"k":[65.875,64.875,0]},"a":{"a":0,"k":[0,0,0]},"s":{"a":0,"k":[213.798,213.798,100]}},"ao":0,"shapes":[{"ty":"gr","it":[{"ty":"rc","d":1,"s":{"a":0,"k":[35.412,9.046]},"p":{"a":0,"k":[0,0]},"r":{"a":0,"k":20},"nm":"Rectangle Path 1","mn":"ADBE Vector Shape - Rect"},{"ty":"st","c":{"a":0,"k":[0,0.82,0.757,1]},"o":{"a":0,"k":100},"w":{"a":0,"k":1},"lc":1,"lj":1,"ml":4,"nm":"Stroke 1","mn":"ADBE Vector Graphic - Stroke"},{"ty":"fl","c":{"a":0,"k":[1,1,1,1]},"o":{"a":0,"k":100},"r":1,"nm":"Fill 1","mn":"ADBE Vector Graphic - Fill"},{"ty":"tr","p":{"a":0,"k":[1.956,3.773],"ix":2},"a":{"a":0,"k":[0,0],"ix":1},"s":{"a":1,"k":[{"i":{"x":[0.833,0.833],"y":[0.833,0.833]},"o":{"x":[0.167,0.167],"y":[0.167,0.167]},"n":["0p833_0p833_0p167_0p167","0p833_0p833_0p167_0p167"],"t":0,"s":[100,100],"e":[120,120]},{"i":{"x":[0.833,0.833],"y":[0.833,0.833]},"o":{"x":[0.167,0.167],"y":[0.167,0.167]},"n":["0p833_0p833_0p167_0p167","0p833_0p833_0p167_0p167"],"t":2,"s":[120,120],"e":[0,0]},{"t":7}],"ix":3},"r":{"a":0,"k":0,"ix":6},"o":{"a":0,"k":100,"ix":7},"sk":{"a":0,"k":0,"ix":4},"sa":{"a":0,"k":0,"ix":5},"nm":"Transform"}],"nm":"Rectangle 1","np":3,"mn":"ADBE Vector Group"}],"ip":0,"op":32,"st":-65,"bm":0,"sr":1},{"ddd":0,"ind":3,"ty":4,"nm":"Bed","ks":{"o":{"a":0,"k":100},"r":{"a":0,"k":0},"p":{"a":0,"k":[69.49,54.236,0]},"a":{"a":0,"k":[0,0,0]},"s":{"a":0,"k":[37.12,37.12,100]}},"ao":0,"shapes":[{"ty":"gr","it":[{"ind":0,"ty":"sh","ks":{"a":1,"k":[{"i":{"x":0,"y":1},"o":{"x":0.167,"y":0.167},"n":"0_1_0p167_0p167","t":11,"s":[{"i":[[2.863,0],[0,0],[0,2.863],[0,0],[-2.863,0],[0,0],[0,-2.863],[0,0]],"o":[[0,0],[-2.863,0],[0,0],[0,-2.863],[0,0],[2.863,0],[0,0],[0,2.863]],"v":[[-11.445,22.984],[-26.883,22.984],[-32.068,17.799],[-32.068,4.685],[-26.883,-0.5],[-11.445,-0.5],[-6.26,4.685],[-6.26,17.799]],"c":true}],"e":[{"i":[[3.717,0],[0,0],[0,3.717],[0,0],[-3.717,0],[0,0],[0,-3.717],[0,0]],"o":[[0,0],[-3.717,0],[0,0],[0,-3.717],[0,0],[3.717,0],[0,0],[0,3.717]],"v":[[-15.229,-21.616],[-35.27,-21.616],[-42,-28.346],[-42,-45.37],[-35.27,-52.1],[-15.229,-52.1],[-8.499,-45.37],[-8.499,-28.346]],"c":true}]},{"i":{"x":0.833,"y":0.833},"o":{"x":0.333,"y":0},"n":"0p833_0p833_0p333_0","t":17,"s":[{"i":[[3.717,0],[0,0],[0,3.717],[0,0],[-3.717,0],[0,0],[0,-3.717],[0,0]],"o":[[0,0],[-3.717,0],[0,0],[0,-3.717],[0,0],[3.717,0],[0,0],[0,3.717]],"v":[[-15.229,-21.616],[-35.27,-21.616],[-42,-28.346],[-42,-45.37],[-35.27,-52.1],[-15.229,-52.1],[-8.499,-45.37],[-8.499,-28.346]],"c":true}],"e":[{"i":[[3.717,0],[0,0],[0,3.717],[0,0],[-3.717,0],[0,0],[0,-3.717],[0,0]],"o":[[0,0],[-3.717,0],[0,0],[0,-3.717],[0,0],[3.717,0],[0,0],[0,3.717]],"v":[[-15.229,-16.116],[-35.27,-16.116],[-42,-22.846],[-42,-39.87],[-35.27,-46.6],[-15.229,-46.6],[-8.499,-39.87],[-8.499,-22.846]],"c":true}]},{"i":{"x":0.667,"y":1},"o":{"x":0.167,"y":0.167},"n":"0p667_1_0p167_0p167","t":21,"s":[{"i":[[3.717,0],[0,0],[0,3.717],[0,0],[-3.717,0],[0,0],[0,-3.717],[0,0]],"o":[[0,0],[-3.717,0],[0,0],[0,-3.717],[0,0],[3.717,0],[0,0],[0,3.717]],"v":[[-15.229,-16.116],[-35.27,-16.116],[-42,-22.846],[-42,-39.87],[-35.27,-46.6],[-15.229,-46.6],[-8.499,-39.87],[-8.499,-22.846]],"c":true}],"e":[{"i":[[3.717,0],[0,0],[0,3.717],[0,0],[-3.717,0],[0,0],[0,-3.717],[0,0]],"o":[[0,0],[-3.717,0],[0,0],[0,-3.717],[0,0],[3.717,0],[0,0],[0,3.717]],"v":[[-15.229,-17.816],[-35.27,-17.816],[-42,-24.546],[-42,-41.57],[-35.27,-48.3],[-15.229,-48.3],[-8.499,-41.57],[-8.499,-24.546]],"c":true}]},{"i":{"x":0.833,"y":0.833},"o":{"x":0.333,"y":0},"n":"0p833_0p833_0p333_0","t":24,"s":[{"i":[[3.717,0],[0,0],[0,3.717],[0,0],[-3.717,0],[0,0],[0,-3.717],[0,0]],"o":[[0,0],[-3.717,0],[0,0],[0,-3.717],[0,0],[3.717,0],[0,0],[0,3.717]],"v":[[-15.229,-17.816],[-35.27,-17.816],[-42,-24.546],[-42,-41.57],[-35.27,-48.3],[-15.229,-48.3],[-8.499,-41.57],[-8.499,-24.546]],"c":true}],"e":[{"i":[[3.717,0],[0,0],[0,3.717],[0,0],[-3.717,0],[0,0],[0,-3.717],[0,0]],"o":[[0,0],[-3.717,0],[0,0],[0,-3.717],[0,0],[3.717,0],[0,0],[0,3.717]],"v":[[-15.229,-15.516],[-35.27,-15.516],[-42,-22.246],[-42,-39.27],[-35.27,-46],[-15.229,-46],[-8.499,-39.27],[-8.499,-22.246]],"c":true}]},{"i":{"x":0.833,"y":0.833},"o":{"x":0.167,"y":0.167},"n":"0p833_0p833_0p167_0p167","t":27,"s":[{"i":[[3.717,0],[0,0],[0,3.717],[0,0],[-3.717,0],[0,0],[0,-3.717],[0,0]],"o":[[0,0],[-3.717,0],[0,0],[0,-3.717],[0,0],[3.717,0],[0,0],[0,3.717]],"v":[[-15.229,-15.516],[-35.27,-15.516],[-42,-22.246],[-42,-39.27],[-35.27,-46],[-15.229,-46],[-8.499,-39.27],[-8.499,-22.246]],"c":true}],"e":[{"i":[[3.717,0],[0,0],[0,3.717],[0,0],[-3.717,0],[0,0],[0,-3.717],[0,0]],"o":[[0,0],[-3.717,0],[0,0],[0,-3.717],[0,0],[3.717,0],[0,0],[0,3.717]],"v":[[-15.229,-15.516],[-35.27,-15.516],[-42,-22.246],[-42,-39.27],[-35.27,-46],[-15.229,-46],[-8.499,-39.27],[-8.499,-22.246]],"c":true}]},{"i":{"x":0.833,"y":0.833},"o":{"x":0.333,"y":0},"n":"0p833_0p833_0p333_0","t":34,"s":[{"i":[[3.717,0],[0,0],[0,3.717],[0,0],[-3.717,0],[0,0],[0,-3.717],[0,0]],"o":[[0,0],[-3.717,0],[0,0],[0,-3.717],[0,0],[3.717,0],[0,0],[0,3.717]],"v":[[-15.229,-15.516],[-35.27,-15.516],[-42,-22.246],[-42,-39.27],[-35.27,-46],[-15.229,-46],[-8.499,-39.27],[-8.499,-22.246]],"c":true}],"e":[{"i":[[0.42,0],[0,0],[0,0.42],[0,0],[-0.42,0],[0,0],[0,-0.42],[0,0]],"o":[[0,0],[-0.42,0],[0,0],[0,-0.42],[0,0],[0.42,0],[0,0],[0,0.42]],"v":[[-8.223,21.766],[-10.489,21.766],[-11.25,21.005],[-11.25,19.08],[-10.489,18.319],[-8.223,18.319],[-7.462,19.08],[-7.462,21.005]],"c":true}]},{"t":37}]},"nm":"Path 1","mn":"ADBE Vector Shape - Group"},{"ty":"st","c":{"a":0,"k":[0,0.82,0.757,1]},"o":{"a":0,"k":100},"w":{"a":0,"k":5},"lc":2,"lj":2,"nm":"Stroke 1","mn":"ADBE Vector Graphic - Stroke"},{"ty":"fl","c":{"a":0,"k":[1,1,1,1]},"o":{"a":0,"k":100},"r":1,"nm":"Fill 1","mn":"ADBE Vector Graphic - Fill"},{"ty":"tr","p":{"a":0,"k":[0,0],"ix":2},"a":{"a":0,"k":[0,0],"ix":1},"s":{"a":0,"k":[100,100],"ix":3},"r":{"a":0,"k":0,"ix":6},"o":{"a":1,"k":[{"i":{"x":[0.833],"y":[0.833]},"o":{"x":[0.167],"y":[0.167]},"n":["0p833_0p833_0p167_0p167"],"t":10,"s":[0],"e":[100]},{"i":{"x":[0.833],"y":[0.833]},"o":{"x":[0.167],"y":[0.167]},"n":["0p833_0p833_0p167_0p167"],"t":11,"s":[100],"e":[100]},{"i":{"x":[0.833],"y":[0.833]},"o":{"x":[0.167],"y":[0.167]},"n":["0p833_0p833_0p167_0p167"],"t":37,"s":[100],"e":[0]},{"t":38}],"ix":7},"sk":{"a":0,"k":0,"ix":4},"sa":{"a":0,"k":0,"ix":5},"nm":"Transform"}],"nm":"Pillow Left","np":3,"mn":"ADBE Vector Group"},{"ty":"gr","it":[{"ind":0,"ty":"sh","ks":{"a":1,"k":[{"i":{"x":0,"y":1},"o":{"x":0.167,"y":0.167},"n":"0_1_0p167_0p167","t":11,"s":[{"i":[[2.863,0],[0,0],[0,2.863],[0,0],[-2.863,0],[0,0],[0,-2.863],[0,0]],"o":[[0,0],[-2.863,0],[0,0],[0,-2.863],[0,0],[2.863,0],[0,0],[0,2.863]],"v":[[27.844,22.984],[12.406,22.984],[7.221,17.799],[7.221,4.685],[12.406,-0.5],[27.844,-0.5],[33.029,4.685],[33.029,17.799]],"c":true}],"e":[{"i":[[3.717,0],[0,0],[0,3.717],[0,0],[-3.717,0],[0,0],[0,-3.717],[0,0]],"o":[[0,0],[-3.717,0],[0,0],[0,-3.717],[0,0],[3.717,0],[0,0],[0,3.717]],"v":[[35.771,-24.866],[15.73,-24.866],[9,-31.596],[9,-48.62],[15.73,-55.35],[35.771,-55.35],[42.501,-48.62],[42.501,-31.596]],"c":true}]},{"i":{"x":0.833,"y":0.833},"o":{"x":0.333,"y":0},"n":"0p833_0p833_0p333_0","t":17,"s":[{"i":[[3.717,0],[0,0],[0,3.717],[0,0],[-3.717,0],[0,0],[0,-3.717],[0,0]],"o":[[0,0],[-3.717,0],[0,0],[0,-3.717],[0,0],[3.717,0],[0,0],[0,3.717]],"v":[[35.771,-24.866],[15.73,-24.866],[9,-31.596],[9,-48.62],[15.73,-55.35],[35.771,-55.35],[42.501,-48.62],[42.501,-31.596]],"c":true}],"e":[{"i":[[3.717,0],[0,0],[0,3.717],[0,0],[-3.717,0],[0,0],[0,-3.717],[0,0]],"o":[[0,0],[-3.717,0],[0,0],[0,-3.717],[0,0],[3.717,0],[0,0],[0,3.717]],"v":[[35.771,-16.116],[15.73,-16.116],[9,-22.846],[9,-39.87],[15.73,-46.6],[35.771,-46.6],[42.501,-39.87],[42.501,-22.846]],"c":true}]},{"i":{"x":0.667,"y":1},"o":{"x":0.167,"y":0.167},"n":"0p667_1_0p167_0p167","t":21,"s":[{"i":[[3.717,0],[0,0],[0,3.717],[0,0],[-3.717,0],[0,0],[0,-3.717],[0,0]],"o":[[0,0],[-3.717,0],[0,0],[0,-3.717],[0,0],[3.717,0],[0,0],[0,3.717]],"v":[[35.771,-16.116],[15.73,-16.116],[9,-22.846],[9,-39.87],[15.73,-46.6],[35.771,-46.6],[42.501,-39.87],[42.501,-22.846]],"c":true}],"e":[{"i":[[3.717,0],[0,0],[0,3.717],[0,0],[-3.717,0],[0,0],[0,-3.717],[0,0]],"o":[[0,0],[-3.717,0],[0,0],[0,-3.717],[0,0],[3.717,0],[0,0],[0,3.717]],"v":[[35.771,-17.816],[15.73,-17.816],[9,-24.546],[9,-41.57],[15.73,-48.3],[35.771,-48.3],[42.501,-41.57],[42.501,-24.546]],"c":true}]},{"i":{"x":0.833,"y":0.833},"o":{"x":0.333,"y":0},"n":"0p833_0p833_0p333_0","t":24,"s":[{"i":[[3.717,0],[0,0],[0,3.717],[0,0],[-3.717,0],[0,0],[0,-3.717],[0,0]],"o":[[0,0],[-3.717,0],[0,0],[0,-3.717],[0,0],[3.717,0],[0,0],[0,3.717]],"v":[[35.771,-17.816],[15.73,-17.816],[9,-24.546],[9,-41.57],[15.73,-48.3],[35.771,-48.3],[42.501,-41.57],[42.501,-24.546]],"c":true}],"e":[{"i":[[3.717,0],[0,0],[0,3.717],[0,0],[-3.717,0],[0,0],[0,-3.717],[0,0]],"o":[[0,0],[-3.717,0],[0,0],[0,-3.717],[0,0],[3.717,0],[0,0],[0,3.717]],"v":[[35.771,-15.516],[15.73,-15.516],[9,-22.246],[9,-39.27],[15.73,-46],[35.771,-46],[42.501,-39.27],[42.501,-22.246]],"c":true}]},{"i":{"x":0.833,"y":0.833},"o":{"x":0.167,"y":0.167},"n":"0p833_0p833_0p167_0p167","t":27,"s":[{"i":[[3.717,0],[0,0],[0,3.717],[0,0],[-3.717,0],[0,0],[0,-3.717],[0,0]],"o":[[0,0],[-3.717,0],[0,0],[0,-3.717],[0,0],[3.717,0],[0,0],[0,3.717]],"v":[[35.771,-15.516],[15.73,-15.516],[9,-22.246],[9,-39.27],[15.73,-46],[35.771,-46],[42.501,-39.27],[42.501,-22.246]],"c":true}],"e":[{"i":[[3.717,0],[0,0],[0,3.717],[0,0],[-3.717,0],[0,0],[0,-3.717],[0,0]],"o":[[0,0],[-3.717,0],[0,0],[0,-3.717],[0,0],[3.717,0],[0,0],[0,3.717]],"v":[[35.771,-15.516],[15.73,-15.516],[9,-22.246],[9,-39.27],[15.73,-46],[35.771,-46],[42.501,-39.27],[42.501,-22.246]],"c":true}]},{"i":{"x":0.833,"y":0.833},"o":{"x":0.333,"y":0},"n":"0p833_0p833_0p333_0","t":34,"s":[{"i":[[3.717,0],[0,0],[0,3.717],[0,0],[-3.717,0],[0,0],[0,-3.717],[0,0]],"o":[[0,0],[-3.717,0],[0,0],[0,-3.717],[0,0],[3.717,0],[0,0],[0,3.717]],"v":[[35.771,-15.516],[15.73,-15.516],[9,-22.246],[9,-39.27],[15.73,-46],[35.771,-46],[42.501,-39.27],[42.501,-22.246]],"c":true}],"e":[{"i":[[0.364,0],[0,0],[0,0.364],[0,0],[-0.364,0],[0,0],[0,-0.364],[0,0]],"o":[[0,0],[-0.364,0],[0,0],[0,-0.364],[0,0],[0.364,0],[0,0],[0,0.364]],"v":[[10.838,21.534],[8.876,21.534],[8.217,20.875],[8.217,19.209],[8.876,18.55],[10.838,18.55],[11.497,19.209],[11.497,20.875]],"c":true}]},{"t":37}]},"nm":"Path 1","mn":"ADBE Vector Shape - Group"},{"ty":"st","c":{"a":0,"k":[0,0.82,0.757,1]},"o":{"a":0,"k":100},"w":{"a":0,"k":5},"lc":2,"lj":2,"nm":"Stroke 1","mn":"ADBE Vector Graphic - Stroke"},{"ty":"fl","c":{"a":0,"k":[1,1,1,1]},"o":{"a":0,"k":100},"r":1,"nm":"Fill 1","mn":"ADBE Vector Graphic - Fill"},{"ty":"tr","p":{"a":0,"k":[0,0],"ix":2},"a":{"a":0,"k":[0,0],"ix":1},"s":{"a":0,"k":[100,100],"ix":3},"r":{"a":0,"k":0,"ix":6},"o":{"a":1,"k":[{"i":{"x":[0.833],"y":[0.833]},"o":{"x":[0.167],"y":[0.167]},"n":["0p833_0p833_0p167_0p167"],"t":10,"s":[0],"e":[100]},{"i":{"x":[0.833],"y":[0.833]},"o":{"x":[0.167],"y":[0.167]},"n":["0p833_0p833_0p167_0p167"],"t":11,"s":[100],"e":[100]},{"i":{"x":[0.833],"y":[0.833]},"o":{"x":[0.167],"y":[0.167]},"n":["0p833_0p833_0p167_0p167"],"t":37,"s":[100],"e":[0]},{"t":38}],"ix":7},"sk":{"a":0,"k":0,"ix":4},"sa":{"a":0,"k":0,"ix":5},"nm":"Transform"}],"nm":"Pillow Right","np":3,"mn":"ADBE Vector Group"},{"ty":"gr","it":[{"ind":0,"ty":"sh","ks":{"a":1,"k":[{"i":{"x":0.833,"y":0.833},"o":{"x":0.167,"y":0.167},"n":"0p833_0p833_0p167_0p167","t":7,"s":[{"i":[[0,0],[0,0]],"o":[[0,0],[0,0]],"v":[[3.84,66.601],[-4.765,66.601]],"c":false}],"e":[{"i":[[0,0],[0,0]],"o":[[0,0],[0,0]],"v":[[29.486,47.991],[-29.964,47.991]],"c":false}]},{"i":{"x":0,"y":1},"o":{"x":0.167,"y":0.167},"n":"0_1_0p167_0p167","t":10,"s":[{"i":[[0,0],[0,0]],"o":[[0,0],[0,0]],"v":[[29.486,47.991],[-29.964,47.991]],"c":false}],"e":[{"i":[[0,0],[0,0]],"o":[[0,0],[0,0]],"v":[[59.498,-20.009],[-59.952,-20.009]],"c":false}]},{"i":{"x":0.833,"y":0.833},"o":{"x":0.167,"y":0.167},"n":"0p833_0p833_0p167_0p167","t":17,"s":[{"i":[[0,0],[0,0]],"o":[[0,0],[0,0]],"v":[[59.498,-20.009],[-59.952,-20.009]],"c":false}],"e":[{"i":[[0,0],[0,0]],"o":[[0,0],[0,0]],"v":[[59.498,-20.009],[-59.952,-20.009]],"c":false}]},{"i":{"x":0,"y":1},"o":{"x":0.333,"y":0},"n":"0_1_0p333_0","t":34,"s":[{"i":[[0,0],[0,0]],"o":[[0,0],[0,0]],"v":[[59.498,-20.009],[-59.952,-20.009]],"c":false}],"e":[{"i":[[0,0],[0,0]],"o":[[0,0],[0,0]],"v":[[25.996,28.982],[-26.454,28.982]],"c":false}]},{"t":41}]},"nm":"Path 1","mn":"ADBE Vector Shape - Group"},{"ty":"st","c":{"a":0,"k":[0,0.82,0.757,1]},"o":{"a":0,"k":100},"w":{"a":0,"k":5},"lc":2,"lj":2,"nm":"Stroke 1","mn":"ADBE Vector Graphic - Stroke"},{"ty":"tr","p":{"a":0,"k":[0,0],"ix":2},"a":{"a":0,"k":[0,0],"ix":1},"s":{"a":0,"k":[100,100],"ix":3},"r":{"a":0,"k":0,"ix":6},"o":{"a":0,"k":100,"ix":7},"sk":{"a":0,"k":0,"ix":4},"sa":{"a":0,"k":0,"ix":5},"nm":"Transform"}],"nm":"Headboard","np":2,"mn":"ADBE Vector Group"},{"ty":"gr","it":[{"ind":0,"ty":"sh","ks":{"a":1,"k":[{"i":{"x":0.833,"y":0.833},"o":{"x":0.167,"y":0.167},"n":"0p833_0p833_0p167_0p167","t":7,"s":[{"i":[[0,0],[0,0]],"o":[[0,0],[0,0]],"v":[[-4.818,67.082],[3.903,67.082]],"c":false}],"e":[{"i":[[0,0],[0,0]],"o":[[0,0],[0,0]],"v":[[-30.332,51.314],[29.918,51.314]],"c":false}]},{"i":{"x":0,"y":1},"o":{"x":0.167,"y":0.167},"n":"0_1_0p167_0p167","t":10,"s":[{"i":[[0,0],[0,0]],"o":[[0,0],[0,0]],"v":[[-30.332,51.314],[29.918,51.314]],"c":false}],"e":[{"i":[[0,0],[0,0]],"o":[[0,0],[0,0]],"v":[[-87.76,32.314],[87.74,32.314]],"c":false}]},{"i":{"x":0.833,"y":0.833},"o":{"x":0.167,"y":0.167},"n":"0p833_0p833_0p167_0p167","t":17,"s":[{"i":[[0,0],[0,0]],"o":[[0,0],[0,0]],"v":[[-87.76,32.314],[87.74,32.314]],"c":false}],"e":[{"i":[[0,0],[0,0]],"o":[[0,0],[0,0]],"v":[[-87.76,32.314],[87.74,32.314]],"c":false}]},{"i":{"x":0,"y":1},"o":{"x":0.333,"y":0},"n":"0_1_0p333_0","t":34,"s":[{"i":[[0,0],[0,0]],"o":[[0,0],[0,0]],"v":[[-87.76,32.314],[87.74,32.314]],"c":false}],"e":[{"i":[[0,0],[0,0]],"o":[[0,0],[0,0]],"v":[[-25.539,47.127],[26.961,47.127]],"c":false}]},{"t":41}]},"nm":"Path 1","mn":"ADBE Vector Shape - Group"},{"ty":"st","c":{"a":0,"k":[0,0.82,0.757,1]},"o":{"a":0,"k":100},"w":{"a":0,"k":5},"lc":2,"lj":2,"nm":"Stroke 1","mn":"ADBE Vector Graphic - Stroke"},{"ty":"tr","p":{"a":0,"k":[0,0],"ix":2},"a":{"a":0,"k":[0,0],"ix":1},"s":{"a":0,"k":[100,100],"ix":3},"r":{"a":0,"k":0,"ix":6},"o":{"a":0,"k":100,"ix":7},"sk":{"a":0,"k":0,"ix":4},"sa":{"a":0,"k":0,"ix":5},"nm":"Transform"}],"nm":"Baseboard","np":2,"mn":"ADBE Vector Group"},{"ty":"gr","it":[{"ind":0,"ty":"sh","ks":{"a":1,"k":[{"i":{"x":0.833,"y":0.833},"o":{"x":0.167,"y":0.167},"n":"0p833_0p833_0p167_0p167","t":7,"s":[{"i":[[0,0],[0,0],[0.503,0],[0,0],[0,0.503],[0,0],[0,0],[0,0],[-0.715,0],[0,0],[0,-0.715],[0,0]],"o":[[0,0],[0,0.503],[0,0],[-0.503,0],[0,0],[0,0],[0,0],[0,-0.715],[0,0],[0.715,0],[0,0],[0,0]],"v":[[3.904,67.079],[3.905,68.372],[2.995,69.283],[-3.904,69.283],[-4.815,68.372],[-4.816,67.079],[-4.764,66.605],[-4.759,65.795],[-3.463,64.5],[2.55,64.5],[3.846,65.795],[3.84,66.605]],"c":true}],"e":[{"i":[[0,0],[0,0],[3.476,0],[0,0],[0,3.476],[0,0],[0,0],[0,0],[-4.943,0],[0,0],[0,-4.943],[0,0]],"o":[[0,0],[0,3.476],[0,0],[-3.475,0],[0,0],[0,0],[0,0],[0,-4.943],[0,0],[4.943,0],[0,0],[0,0]],"v":[[29.928,51.297],[29.938,60.23],[23.645,66.522],[-24.02,66.522],[-30.312,60.23],[-30.322,51.297],[-29.962,48.022],[-29.924,42.428],[-20.973,33.478],[20.576,33.478],[29.526,42.428],[29.488,48.022]],"c":true}]},{"i":{"x":0,"y":1},"o":{"x":0.167,"y":0.167},"n":"0_1_0p167_0p167","t":10,"s":[{"i":[[0,0],[0,0],[3.476,0],[0,0],[0,3.476],[0,0],[0,0],[0,0],[-4.943,0],[0,0],[0,-4.943],[0,0]],"o":[[0,0],[0,3.476],[0,0],[-3.475,0],[0,0],[0,0],[0,0],[0,-4.943],[0,0],[4.943,0],[0,0],[0,0]],"v":[[29.928,51.297],[29.938,60.23],[23.645,66.522],[-24.02,66.522],[-30.312,60.23],[-30.322,51.297],[-29.962,48.022],[-29.924,42.428],[-20.973,33.478],[20.576,33.478],[29.526,42.428],[29.488,48.022]],"c":true}],"e":[{"i":[[0,0],[0,0],[3.476,0],[0,0],[0,3.476],[0,0],[0,0],[0,0],[-4.943,0],[0,0],[0,-4.943],[0,0]],"o":[[0,0],[0,3.476],[0,0],[-3.475,0],[0,0],[0,0],[0,0],[0,-4.943],[0,0],[4.943,0],[0,0],[0,0]],"v":[[87.75,32.297],[87.75,60.23],[81.457,66.522],[-81.457,66.522],[-87.75,60.23],[-87.75,32.297],[-59.95,-19.978],[-59.95,-55.322],[-50.999,-64.272],[50.55,-64.272],[59.5,-55.322],[59.5,-19.978]],"c":true}]},{"i":{"x":0.833,"y":0.833},"o":{"x":0.167,"y":0.167},"n":"0p833_0p833_0p167_0p167","t":17,"s":[{"i":[[0,0],[0,0],[3.476,0],[0,0],[0,3.476],[0,0],[0,0],[0,0],[-4.943,0],[0,0],[0,-4.943],[0,0]],"o":[[0,0],[0,3.476],[0,0],[-3.475,0],[0,0],[0,0],[0,0],[0,-4.943],[0,0],[4.943,0],[0,0],[0,0]],"v":[[87.75,32.297],[87.75,60.23],[81.457,66.522],[-81.457,66.522],[-87.75,60.23],[-87.75,32.297],[-59.95,-19.978],[-59.95,-55.322],[-50.999,-64.272],[50.55,-64.272],[59.5,-55.322],[59.5,-19.978]],"c":true}],"e":[{"i":[[0,0],[0,0],[3.476,0],[0,0],[0,3.476],[0,0],[0,0],[0,0],[-4.943,0],[0,0],[0,-4.943],[0,0]],"o":[[0,0],[0,3.476],[0,0],[-3.475,0],[0,0],[0,0],[0,0],[0,-4.943],[0,0],[4.943,0],[0,0],[0,0]],"v":[[87.75,32.297],[87.75,60.23],[81.457,66.522],[-81.457,66.522],[-87.75,60.23],[-87.75,32.297],[-59.95,-19.978],[-59.95,-55.322],[-50.999,-64.272],[50.55,-64.272],[59.5,-55.322],[59.5,-19.978]],"c":true}]},{"i":{"x":0,"y":1},"o":{"x":0.333,"y":0},"n":"0_1_0p333_0","t":34,"s":[{"i":[[0,0],[0,0],[3.476,0],[0,0],[0,3.476],[0,0],[0,0],[0,0],[-4.943,0],[0,0],[0,-4.943],[0,0]],"o":[[0,0],[0,3.476],[0,0],[-3.475,0],[0,0],[0,0],[0,0],[0,-4.943],[0,0],[4.943,0],[0,0],[0,0]],"v":[[87.75,32.297],[87.75,60.23],[81.457,66.522],[-81.457,66.522],[-87.75,60.23],[-87.75,32.297],[-59.95,-19.978],[-59.95,-55.322],[-50.999,-64.272],[50.55,-64.272],[59.5,-55.322],[59.5,-19.978]],"c":true}],"e":[{"i":[[0,0],[0,0],[3.476,0],[0,0],[0,3.476],[0,0],[0,0],[0,0],[-4.943,0],[0,0],[0,-4.943],[0,0]],"o":[[0,0],[0,3.476],[0,0],[-3.475,0],[0,0],[0,0],[0,0],[0,-4.943],[0,0],[4.943,0],[0,0],[0,0]],"v":[[27,53.896],[27,82.328],[20.707,88.621],[-18.957,88.783],[-25.25,82.49],[-25.25,54.058],[-25.7,37.632],[-25.9,26.538],[-16.949,17.587],[17.35,17.94],[26.3,26.891],[26.5,37.985]],"c":true}]},{"t":41}]},"nm":"Path 1","mn":"ADBE Vector Shape - Group"},{"ty":"st","c":{"a":0,"k":[0,0.82,0.757,1]},"o":{"a":0,"k":100},"w":{"a":0,"k":5},"lc":2,"lj":2,"nm":"Stroke 1","mn":"ADBE Vector Graphic - Stroke"},{"ty":"tr","p":{"a":0,"k":[0,0],"ix":2},"a":{"a":0,"k":[0,0],"ix":1},"s":{"a":0,"k":[100,100],"ix":3},"r":{"a":0,"k":0,"ix":6},"o":{"a":0,"k":100,"ix":7},"sk":{"a":0,"k":0,"ix":4},"sa":{"a":0,"k":0,"ix":5},"nm":"Transform"}],"nm":"Bed","np":2,"mn":"ADBE Vector Group"},{"ty":"gr","it":[{"ind":0,"ty":"sh","ks":{"a":1,"k":[{"i":{"x":0.833,"y":0.833},"o":{"x":0.167,"y":0.167},"n":"0p833_0p833_0p167_0p167","t":7,"s":[{"i":[[0,0],[0,0]],"o":[[0,0],[0,0]],"v":[[-3.749,69.307],[-3.768,69.789]],"c":false}],"e":[{"i":[[0,0],[0,0]],"o":[[0,0],[0,0]],"v":[[-22.946,66.689],[-23.08,70.023]],"c":false}]},{"i":{"x":0,"y":1},"o":{"x":0.167,"y":0.167},"n":"0_1_0p167_0p167","t":10,"s":[{"i":[[0,0],[0,0]],"o":[[0,0],[0,0]],"v":[[-22.946,66.689],[-23.08,70.023]],"c":false}],"e":[{"i":[[0,0],[0,0]],"o":[[0,0],[0,0]],"v":[[-80.384,66.689],[-80.384,80.356]],"c":false}]},{"i":{"x":0.833,"y":0.833},"o":{"x":0.167,"y":0.167},"n":"0p833_0p833_0p167_0p167","t":17,"s":[{"i":[[0,0],[0,0]],"o":[[0,0],[0,0]],"v":[[-80.384,66.689],[-80.384,80.356]],"c":false}],"e":[{"i":[[0,0],[0,0]],"o":[[0,0],[0,0]],"v":[[-80.384,66.689],[-80.384,80.356]],"c":false}]},{"i":{"x":0,"y":1},"o":{"x":0.333,"y":0},"n":"0_1_0p333_0","t":34,"s":[{"i":[[0,0],[0,0]],"o":[[0,0],[0,0]],"v":[[-80.384,66.689],[-80.384,80.356]],"c":false}],"e":[{"i":[[0,0],[0,0]],"o":[[0,0],[0,0]],"v":[[-4.277,88.545],[-4.253,88.612]],"c":false}]},{"t":41}]},"nm":"Path 1","mn":"ADBE Vector Shape - Group"},{"ty":"st","c":{"a":0,"k":[0,0.82,0.757,1]},"o":{"a":0,"k":100},"w":{"a":0,"k":5},"lc":2,"lj":2,"nm":"Stroke 1","mn":"ADBE Vector Graphic - Stroke"},{"ty":"tr","p":{"a":0,"k":[0,0],"ix":2},"a":{"a":0,"k":[0,0],"ix":1},"s":{"a":0,"k":[100,100],"ix":3},"r":{"a":0,"k":0,"ix":6},"o":{"a":0,"k":100,"ix":7},"sk":{"a":0,"k":0,"ix":4},"sa":{"a":0,"k":0,"ix":5},"nm":"Transform"}],"nm":"Leg Left","np":2,"mn":"ADBE Vector Group"},{"ty":"gr","it":[{"ind":0,"ty":"sh","ks":{"a":1,"k":[{"i":{"x":0.833,"y":0.833},"o":{"x":0.167,"y":0.167},"n":"0p833_0p833_0p167_0p167","t":7,"s":[{"i":[[0,0],[0,0]],"o":[[0,0],[0,0]],"v":[[2.796,69.307],[2.777,69.789]],"c":false}],"e":[{"i":[[0,0],[0,0]],"o":[[0,0],[0,0]],"v":[[22.273,66.689],[22.14,70.023]],"c":false}]},{"i":{"x":0,"y":1},"o":{"x":0.167,"y":0.167},"n":"0_1_0p167_0p167","t":10,"s":[{"i":[[0,0],[0,0]],"o":[[0,0],[0,0]],"v":[[22.273,66.689],[22.14,70.023]],"c":false}],"e":[{"i":[[0,0],[0,0]],"o":[[0,0],[0,0]],"v":[[80.086,66.689],[80.086,80.356]],"c":false}]},{"i":{"x":0.833,"y":0.833},"o":{"x":0.167,"y":0.167},"n":"0p833_0p833_0p167_0p167","t":17,"s":[{"i":[[0,0],[0,0]],"o":[[0,0],[0,0]],"v":[[80.086,66.689],[80.086,80.356]],"c":false}],"e":[{"i":[[0,0],[0,0]],"o":[[0,0],[0,0]],"v":[[80.086,66.689],[80.086,80.356]],"c":false}]},{"i":{"x":0,"y":1},"o":{"x":0.333,"y":0},"n":"0_1_0p333_0","t":34,"s":[{"i":[[0,0],[0,0]],"o":[[0,0],[0,0]],"v":[[80.086,66.689],[80.086,80.356]],"c":false}],"e":[{"i":[[0,0],[0,0]],"o":[[0,0],[0,0]],"v":[[7.693,88.59],[7.716,88.657]],"c":false}]},{"t":41}]},"nm":"Path 1","mn":"ADBE Vector Shape - Group"},{"ty":"st","c":{"a":0,"k":[0,0.82,0.757,1]},"o":{"a":0,"k":100},"w":{"a":0,"k":5},"lc":2,"lj":2,"nm":"Stroke 1","mn":"ADBE Vector Graphic - Stroke"},{"ty":"tr","p":{"a":0,"k":[0,0],"ix":2},"a":{"a":0,"k":[0,0],"ix":1},"s":{"a":0,"k":[100,100],"ix":3},"r":{"a":0,"k":0,"ix":6},"o":{"a":0,"k":100,"ix":7},"sk":{"a":0,"k":0,"ix":4},"sa":{"a":0,"k":0,"ix":5},"nm":"Transform"}],"nm":"Leg Right","np":2,"mn":"ADBE Vector Group"}],"ip":7,"op":43,"st":-18,"bm":0,"sr":1}]}